<?xml version="1.0" encoding="UTF-8"?>
<StructureDefinition
    xmlns="http://hl7.org/fhir">
    <id value="colon-rectum-resection-presurgical-therapy-procedure-us"/>
    <meta>
        <versionId value="2"/>
        <lastUpdated value="2021-03-05T19:06:47.672+00:00"/>
        <source value="#C4Si95VGOr5ci5LU"/>
    </meta>
    <url value="http://www.hl7.org/fhir/us/cancer-reporting/StructureDefinition/colon-rectum-resection-presurgical-therapy-procedure-us"/>
    <name value="ColonRectumPresurgicalTherapy"/>
    <title value="Colon/Rectum Presurgical Therapy"/>
    <status value="active"/>
    <description value="Whther pre-surgical Treatment Effect of Colon/Rectum is observed or not, and if observed, the score of the response to the treatment)."/>
    <fhirVersion value="4.0.1"/>
    <kind value="resource"/>
    <abstract value="false"/>
    <type value="Procedure"/>
    <baseDefinition value="http://hl7.org/fhir/us/core/StructureDefinition/us-core-procedure"/>
    <derivation value="constraint"/>
    <differential>
        <element id="Procedure">
            <path value="Procedure"/>
        </element>
    </differential>
</StructureDefinition>